invoice_generator/__init__.py
invoice_generator/invoice_generator.py
invoice_generator/models.py
invoice_generator/templates/base.tex
invoice_generator/templates/invoice.cls
invoice_generator/templates/main.tex
invoice_generator/templates/payment.tex
invoice_generator/templates/prestations_block.tex
invoice_generator/templates/total_block.tex
french_invoice_generator-0.3.dist-info/AUTHORS.rst
french_invoice_generator-0.3.dist-info/LICENSE
french_invoice_generator-0.3.dist-info/METADATA
french_invoice_generator-0.3.dist-info/WHEEL
french_invoice_generator-0.3.dist-info/top_level.txt
french_invoice_generator-0.3.dist-info/RECORD
