Metadata-Version: 2.1
Name: french-invoice-generator
Version: 0.3
Summary: generate french invoices with latex from python
Home-page: https://github.com/tgrandjean/french-invoice-generator
Author: Thibault Grandjean
Author-email: thibault@cornet-grandjean.com
License: Apache Software License 2.0
Keywords: invoice_generator
Platform: UNKNOWN
Classifier: Development Status :: 2 - Pre-Alpha
Classifier: Intended Audience :: Developers
Classifier: License :: OSI Approved :: Apache Software License
Classifier: Natural Language :: English
Classifier: Programming Language :: Python :: 3
Classifier: Programming Language :: Python :: 3.6
Classifier: Programming Language :: Python :: 3.7
Classifier: Programming Language :: Python :: 3.8
Requires-Python: >=3.6
License-File: LICENSE
License-File: AUTHORS.rst
Requires-Dist: pydantic (==1.8.2)
Requires-Dist: Jinja2 (==3.0.2)
Requires-Dist: email-validator (==1.1.3)
